{
  "MiniTest": {
    "coverage": {
      "/app/test/controllers/web/developers_controller_test.rb": [
        1,
        null,
        1,
        1,
        0,
        0,
        null,
        null,
        1,
        0,
        0,
        null,
        null
      ],
      "/app/test/controllers/web/sessions_controller_test.rb": [
        1,
        null,
        1,
        1,
        0,
        0,
        null,
        null,
        1,
        0,
        0,
        0,
        0,
        null,
        null,
        null,
        0,
        0,
        null,
        null,
        1,
        0,
        0,
        null,
        null
      ],
      "/app/test/models/admin_test.rb": [
        1,
        null,
        1,
        null,
        null,
        null,
        null
      ],
      "/app/test/models/developer_test.rb": [
        1,
        null,
        1,
        null,
        null,
        null,
        null
      ],
      "/app/test/models/manager_test.rb": [
        1,
        null,
        1,
        null,
        null,
        null,
        null
      ],
      "/app/test/models/task_test.rb": [
        1,
        null,
        1,
        null,
        null,
        null,
        null
      ],
      "/app/test/models/user_test.rb": [
        1,
        null,
        1,
        null,
        null,
        null,
        null
      ]
    },
    "timestamp": 1553432950
  }
}
